dsversion/__init__.py
dsversion-0.0.3.dist-info/METADATA
dsversion-0.0.3.dist-info/WHEEL
dsversion-0.0.3.dist-info/top_level.txt
dsversion-0.0.3.dist-info/RECORD
